LICENSE
MANIFEST.in
setup.py
filebrowser/__init__.py
filebrowser/admin.py
filebrowser/base.py
filebrowser/forms.py
filebrowser/models.py
filebrowser/settings.py
filebrowser/signals.py
filebrowser/utils.py
filebrowser/locale/ru/LC_MESSAGES/django.mo
filebrowser/locale/ru/LC_MESSAGES/django.po
filebrowser/locale/ru/LC_MESSAGES/djangojs.mo
filebrowser/locale/ru/LC_MESSAGES/djangojs.po
filebrowser/static/filebrowser/css/style.css
filebrowser/static/filebrowser/images/icons/delete.gif
filebrowser/static/filebrowser/images/icons/delete_hover.gif
filebrowser/static/filebrowser/images/icons/rename.gif
filebrowser/static/filebrowser/images/icons/rename_hover.gif
filebrowser/static/filebrowser/images/icons/show.gif
filebrowser/static/filebrowser/images/icons/show_hover.gif
filebrowser/static/filebrowser/images/types/audio.gif
filebrowser/static/filebrowser/images/types/code.gif
filebrowser/static/filebrowser/images/types/document.gif
filebrowser/static/filebrowser/images/types/folder.gif
filebrowser/static/filebrowser/images/types/image.gif
filebrowser/static/filebrowser/images/types/unknown.gif
filebrowser/static/filebrowser/images/types/video.gif
filebrowser/static/filebrowser/js/tiny_mce_popup.js
filebrowser/templates/filebrowser/browse.html
filebrowser/templates/filebrowser/makedir.html
filebrowser/templates/filebrowser/rename.html
filebrowser/templates/filebrowser/upload.html
filebrowser/templates/filebrowser/include/breadcrumbs.html
filebrowser/templates/filebrowser/include/filelisting.html
filebrowser/templates/filebrowser/include/filter.html
filebrowser/templates/filebrowser/include/tableheader.html
filebrowser/templates/filebrowser/include/toolbar.html
filebrowser/templates/filebrowser/tags/paginator.html
filebrowser/templatetags/__init__.py
filebrowser/templatetags/filebrowser.py
lemon_filebrowser.egg-info/PKG-INFO
lemon_filebrowser.egg-info/SOURCES.txt
lemon_filebrowser.egg-info/dependency_links.txt
lemon_filebrowser.egg-info/top_level.txt