Metadata-Version: 1.1
Name: lemon-filebrowser
Version: 0.1.2
Summary: Fork of Patrick Kranzlmueller's django-filebrowser app.
Home-page: https://github.com/trilan/lemon-filebrowser
Author: Trilan Team
Author-email: dev@lemon.io
License: ISC
Platform: UNKNOWN
Classifier: Development Status :: 3 - Alpha
Classifier: Framework :: Django
Classifier: Intended Audience :: Developers
Classifier: License :: OSI Approved :: ISC License (ISCL)
Classifier: Operating System :: OS Independent
Classifier: Programming Language :: Python
Classifier: Programming Language :: Python :: 2.6
Classifier: Programming Language :: Python :: 2.7
Classifier: Topic :: Internet :: WWW/HTTP
